chronometrage/__init__.py
chronometrage/chronometrage.py
chronometrage/README.md
chronometrage-0.1.3.1.dist-info/WHEEL
chronometrage-0.1.3.1.dist-info/METADATA
chronometrage-0.1.3.1.dist-info/RECORD
