Metadata-Version: 2.1
Name: chronometrage
Version: 0.1.3.1
Summary: 
Author: Pierre Lemaitre
Author-email: oultetman@sfr.fr
Requires-Python: >=3.9,<4.0
Classifier: Programming Language :: Python :: 3
Classifier: Programming Language :: Python :: 3.10
Classifier: Programming Language :: Python :: 3.9
